hrbot/__init__.py
hrbot/bot/__init__.py
hrbot/bot/base.py
hrbot/bot/bot.py
hrbot/dispatcher/__init__.py
hrbot/dispatcher/dispatсher.py
hrbot/dispatcher/filter.py
hrbot/dispatcher/fsm/__init__.py
hrbot/dispatcher/fsm/state.py
hrbot/dispatcher/fsm/storage.py
hrbot/dispatcher/handler.py
hrbot/types/__init__.py
hrbot/types/handler.py
hrbot/types/hr.py
hrbot/utils/__init__.py
hrbot-0.1.4.dist-info/LICENSE
hrbot-0.1.4.dist-info/METADATA
hrbot-0.1.4.dist-info/WHEEL
hrbot-0.1.4.dist-info/RECORD
