Metadata-Version: 2.1
Name: hrbot
Version: 0.1.4
Summary: The hrbot is a wrapper on top of the HighRise Python Bot SDK that makes it easy to create bots in HighRise.
License: MIT
Author: MuoDosta
Author-email: MuoDostaWork@gmail.com
Requires-Python: >=3.10,<4.0
Classifier: License :: OSI Approved :: MIT License
Classifier: Programming Language :: Python :: 3
Classifier: Programming Language :: Python :: 3.10
Classifier: Programming Language :: Python :: 3.11
Requires-Dist: highrise-bot-sdk (==23.3.0)
Requires-Dist: redis (==4.5.5)
